<?xml version="1.0" encoding="utf-8"?>

<aiscript name="JP_TestMod" xmlns:xsi="http://www.w3.org/2001/XMLSchema-instance" xsi:noNamespaceSchemaLocation="aiscripts.xsd" version="1">

  <order id="JP_TestMod" name="JP TestScript" category="navigation" infinite="false">
    <params>
      <!-- DEBUG -->
      <param name="DEBUG" text="DebugText" type="number" default="0" advanced="1">
        <input_param name="step" value="50"/>
        <input_param name="min" value="0"/>
        <input_param name="max" value="100"/>
      </param>
    </params>
    <skill min="0"/>
    <requires>
      <match shiptype="shiptype.lasertower" negate="true"/>
    </requires>
  </order>

  <interrupts>
    <handler ref="SectorChangeHandler"/>
    <handler ref="TargetInvalidHandler"/>
    <handler ref="AttackHandler"/>
    <handler ref="MissileLockHandler" />
    <handler ref="ScannedHandler"/>
    <handler ref="InspectedHandler"/>
    <handler ref="FoundAbandonedHandler"/>
    <handler ref="FoundLockboxHandler"/>
    <handler ref="ResupplyHandler"/>
    <handler ref="JobRemoveRequestHandler" />
  </interrupts>

  <init>
  </init>

  <attention min="unknown">
    <actions>

      <wait exact="1ms"/>
      <label name="START"/>
      <cancel_all_orders object="this.ship"/>

      <!-- ~~~~~~~~~~~~~~~~~~~~~~~~~~~~~~~~~~~~~~~~~~~~~~~~~~~~ -->
     
      <!-- ~~~~~~~~~~~~~~~~~~~~~~~~~~~~~~~~~~~~~~~~~~~~~~~~~~~~ -->

      <label name="FINISH"/>
      <set_order_syncpoint_reached order="this.ship.order"/>
      <cancel_order order="this.ship.order" />
      <wait exact="1ms"/>

    </actions>
  </attention>

</aiscript>