<?xml version="1.0" encoding="UTF-8"?>
<!-- Japanese ~~ 日本語 -->
<language>
  <page id="8888888" voice="no">
    <!--  JP_AnotherExplorerV2 -->
    <t id="400">敵セクター？</t>
    <t id="401">中立セクター？</t>
    <t id="402">友好的なセクター？</t>
    <t id="403">不明なセクター？</t>
    <t id="410">ゲート?</t>
    <t id="411">ステーション?</t>
    <t id="412">敵ステーション？</t>
    <t id="413">友好的なステーション？</t>
    <t id="420">オートマチック艦隊?</t>
    <t id="421">艦隊のリーダーですか？</t>
    <t id="422">艦隊名を色付けする？</t>
    <t id="460">注文設定を保存しました。</t>
    <t id="461">注文設定が再設定されました。</t>
    <t id="470">透明性</t>
    <t id="471">赤色</t>
    <t id="472">緑色</t>
    <t id="473">黒色</t>
    <t id="480">アイドル：タイム</t>
    <t id="481">アイドル：フォロー?</t>
    <t id="482">誰をフォローしますか？</t>
    <t id="483">アイドル：ドッキング？</t>
    <t id="484">どこにドッキングしますか？</t>
    <t id="485">アイドル：ランダムな動き？</t>
    <t id="486">どのセクターで？</t>
    <t id="487">アイドル：移動しますか？</t>
    <t id="488">どこに移動しますか？</t>
    <t id="494">注文タグを追加しますか？</t>
    <t id="495">注文設定を保存しますか？</t>
    <t id="496">注文設定をリセットする？</t>
    <t id="497">\033#B600CCCC#</t>
    <t id="498">\033#FF00CC66#</t>
    <t id="499">\033X</t>
  </page>
</language>