<?xml version="1.0" encoding="UTF-8"?>
<!-- Japanese ~~ 日本語 -->
<language>
  <page id="8888888" voice="no">
    <!--  JP_CollectDroppedInventory -->
    <t id="2080">アイドルタイム</t>
    <t id="2081">アイドル：フォロー?</t>
    <t id="2082">誰をフォローしますか？</t>
    <t id="2083">アイドル：ドッキング？</t>
    <t id="2084">どこにドッキングしますか？</t>
    <t id="2085">アイドル：ランダムな動き？</t>
    <t id="2086">どのセクターで？</t>
    <t id="2087">アイドル：移動しますか？</t>
    <t id="2088">どこに移動しますか？</t>
    <t id="2091">注文タグを追加しますか？</t>
    <t id="2092">オーダータグの位置</t>
    <t id="2093">注文設定を保存しますか？</t>
    <t id="2094">注文設定をリセットする？</t>
    <t id="2095">注文設定を保存しました。</t>
    <t id="2096">注文設定が再設定されました。</t>
    <t id="2097">\033#B600CCCC#</t>
    <t id="2098">\033#FF00CC66#</t>
    <t id="2099">\033X</t>
  </page>
</language>