<?xml version="1.0" encoding="UTF-8"?>
<!-- Italian ~~ Italiano -->
<language>
  <page id="8888888" voice="no">
    <!-- JP_AddTag -->
    <t id="200">Etichetta frontale?</t> 
    <t id="201">Tag alla fine?</t> 
    <t id="202">Includi comandante?</t> 
    <t id="203">Includi subordinati?</t> 
    <t id="204">Includere i subordinati delle flotte subordinate?</t> 
    <t id="205">Oggetto con tag come nome</t> 
    <t id="206">Colorare il tag?</t> 
    <t id="207">Colora il nome?</t> 
    <t id="230">Salva il nome dei comandanti?</t> 
    <t id="231">Salva i nomi dei subordinati?</t> 
    <t id="232">Salva nomi subordinati sub. Le flotte?</t> 
    <t id="233">Carica il nome dei comandanti?</t> 
    <t id="234">Caricare i nomi dei subordinati?</t> 
    <t id="235">Carica nomi subordinati sub. Le flotte?</t> 
    <t id="236">Reimpostare il nome dei comandanti?</t> 
    <t id="237">Reimpostare i nomi dei subordinati?</t> 
    <t id="238">Ripristina nomi subordinati sub. Le flotte?</t> 
    <t id="239">Elimina il nome dei comandanti?</t> 
    <t id="240">Elimina i nomi dei subordinati?</t> 
    <t id="241">Elimina nomi subordinati sub. Le flotte?</t> 
    <t id="270">Trasparenza</t> 
    <t id="271">Rossa</t> 
    <t id="272">Verde</t> 
    <t id="273">Blu</t> 
    <t id="295">Salva le impostazioni?</t> 
    <t id="296">Elimina impostazioni?</t> 
    <t id="297">\033#B600CCCC#</t>
    <t id="298">\033#FF00CC66#</t>
    <t id="299">\033X</t>
  </page>
</language>